asynccloup/__init__.py
asynccloup/_commands.py
asynccloup/_context.py
asynccloup/_option_groups.py
asynccloup/_params.py
asynccloup/_params.pyi
asynccloup/_sections.py
asynccloup/_util.py
asynccloup/_version.py
asynccloup/py.typed
asynccloup/styling.py
asynccloup/types.py
asynccloup/typing.py
asynccloup/warnings.py
asynccloup/constraints/__init__.py
asynccloup/constraints/_conditional.py
asynccloup/constraints/_core.py
asynccloup/constraints/_support.py
asynccloup/constraints/common.py
asynccloup/constraints/conditions.py
asynccloup/constraints/exceptions.py
asynccloup/formatting/__init__.py
asynccloup/formatting/_formatter.py
asynccloup/formatting/_util.py
asynccloup/formatting/sep.py
asynccloup-3.0.8.2.dist-info/licenses/LICENSE
asynccloup-3.0.8.2.dist-info/METADATA
asynccloup-3.0.8.2.dist-info/WHEEL
asynccloup-3.0.8.2.dist-info/top_level.txt
asynccloup-3.0.8.2.dist-info/RECORD
