Metadata-Version: 2.4
Name: asynccloup
Version: 3.0.8.2
Summary: Adds features to AsyncClick: option groups, constraints, subcommand sections and help themes. A fork of Gianluca Gippetto's 'Cloup'.
Home-page: https://github.com/M-o-a-T/asynccloup
Author: Matthias Urlichs
Author-email: matthias@urlichs.de
License: BSD 3-Clause
Keywords: CLI,click,argument groups,option groups,constraints,help colors,help themes,help styles
Classifier: Intended Audience :: Developers
Classifier: License :: OSI Approved :: BSD License
Classifier: Natural Language :: English
Classifier: Programming Language :: Python :: 3
Classifier: Programming Language :: Python :: 3.9
Classifier: Programming Language :: Python :: 3.10
Classifier: Programming Language :: Python :: 3.11
Classifier: Programming Language :: Python :: 3.12
Classifier: Programming Language :: Python :: 3.13
Requires-Python: >=3.9
License-File: LICENSE
Requires-Dist: anyio<5.0,>=4.10
Requires-Dist: asyncclick<9.0,>=8.0
Requires-Dist: typing_extensions; python_version <= "3.10"
Dynamic: author
Dynamic: author-email
Dynamic: classifier
Dynamic: description
Dynamic: description-content-type
Dynamic: home-page
Dynamic: keywords
Dynamic: license
Dynamic: license-file
Dynamic: requires-dist
Dynamic: requires-python
Dynamic: summary
